Metadata-Version: 2.1
Name: toasync
Version: 0.0.1
Summary: UNKNOWN
Home-page: UNKNOWN
Author: Nguyen Khac Thanh
License: UNKNOWN
Platform: UNKNOWN
